setup.py
asymmetricbase/__init__.py
asymmetricbase/models.py
asymmetricbase.utils.egg-info/PKG-INFO
asymmetricbase.utils.egg-info/SOURCES.txt
asymmetricbase.utils.egg-info/dependency_links.txt
asymmetricbase.utils.egg-info/namespace_packages.txt
asymmetricbase.utils.egg-info/requires.txt
asymmetricbase.utils.egg-info/top_level.txt
asymmetricbase/management/__init__.py
asymmetricbase/management/commands/__init__.py
asymmetricbase/management/commands/adduser.py
asymmetricbase/management/commands/recreate_fkeys.py
asymmetricbase/middleware/__init__.py
asymmetricbase/middleware/request_cache.py
asymmetricbase/middleware/timezone.py
asymmetricbase/tests/__init__.py
asymmetricbase/tests/cached_function.py
asymmetricbase/utils/__init__.py
asymmetricbase/utils/cached_function.py
asymmetricbase/utils/caching.py
asymmetricbase/utils/exceptions.py
asymmetricbase/utils/highlighter.py
asymmetricbase/utils/jsonencoder.py
asymmetricbase/utils/meta_decorator.py
asymmetricbase/utils/monkey_patch_django_auth_models.py
asymmetricbase/utils/monkey_patching.py
asymmetricbase/utils/month_iter.py
asymmetricbase/utils/orderedset.py
asymmetricbase/utils/permission_decorators.py
asymmetricbase/utils/permissions.py
asymmetricbase/utils/resources.py
asymmetricbase/utils/theme_loader.py