Metadata-Version: 1.1
Name: asymmetricbase.utils
Version: 0.1.4-201404241723
Summary: Utilies for Asymmetric Base Framework
Home-page: https://github.com/AsymmetricVentures/asym-utils
Author: Richard Eames
Author-email: reames@asymmetricventures.com
License: GPLv2
Download-URL: https://github.com/AsymmetricVentures/asym-utils/archive/v0.1.4.tar.gz
Platform: UNKNOWN
Classifier: Development Status :: 4 - Beta
Classifier: Framework :: Django
Classifier: Programming Language :: Python
Classifier: Intended Audience :: Developers
Classifier: Natural Language :: English
Classifier: Operating System :: OS Independent
Classifier: Topic :: Software Development :: Libraries
Classifier: Topic :: Utilities
Classifier: License :: OSI Approved :: GNU General Public License v2 (GPLv2)
Classifier: Topic :: Software Development :: Libraries :: Application Frameworks
